nxlc.py
nxlc-0.1.3.dist-info/licenses/LICENSE
nxlc-0.1.3.dist-info/METADATA
nxlc-0.1.3.dist-info/WHEEL
nxlc-0.1.3.dist-info/entry_points.txt
nxlc-0.1.3.dist-info/top_level.txt
nxlc-0.1.3.dist-info/RECORD
