Metadata-Version: 2.4
Name: nxlc
Version: 0.1.3
Summary: NeoAxios Language Counter - Fast line counting for 119+ programming languages
Author-email: NeoAxios <226793947+neoaxios-dev@users.noreply.github.com>
Maintainer-email: NeoAxios <226793947+neoaxios-dev@users.noreply.github.com>
License-Expression: MIT
Project-URL: Homepage, https://github.com/neoaxios/nxlc
Project-URL: Repository, https://github.com/neoaxios/nxlc
Project-URL: Documentation, https://github.com/neoaxios/nxlc#readme
Project-URL: Bug Tracker, https://github.com/neoaxios/nxlc/issues
Project-URL: Changelog, https://github.com/neoaxios/nxlc/blob/main/CHANGELOG.md
Keywords: code-analysis,line-counter,programming-languages,git-integration,cloc,sloccount,tokei,development-tools
Classifier: Development Status :: 3 - Alpha
Classifier: Intended Audience :: Developers
Classifier: Operating System :: OS Independent
Classifier: Programming Language :: Python :: 3
Classifier: Programming Language :: Python :: 3.8
Classifier: Programming Language :: Python :: 3.9
Classifier: Programming Language :: Python :: 3.10
Classifier: Programming Language :: Python :: 3.11
Classifier: Programming Language :: Python :: 3.12
Classifier: Topic :: Software Development :: Libraries :: Python Modules
Classifier: Topic :: Software Development :: Quality Assurance
Classifier: Topic :: System :: Systems Administration
Classifier: Topic :: Utilities
Classifier: Environment :: Console
Requires-Python: >=3.8
License-File: LICENSE
Provides-Extra: enhanced
Requires-Dist: chardet>=4.0.0; extra == "enhanced"
Provides-Extra: dev
Requires-Dist: chardet>=4.0.0; extra == "dev"
Requires-Dist: pytest>=6.0; extra == "dev"
Requires-Dist: black; extra == "dev"
Requires-Dist: flake8; extra == "dev"
Dynamic: license-file
